{
  "$schema": "../SYNAPSE-SCHEMA.json",
  "skillId": "hr-people-operations",
  "version": "1.1.0",
  "lastUpdated": "2026-04-13",
  "connections": [
    {
      "target": ".github/skills/coaching-techniques/SKILL.md",
      "type": "extends",
      "strength": 0.8,
      "description": "HR uses coaching frameworks for performance management and employee development",
      "when": "HR people operations enhances coaching techniques",
      "yields": "coaching techniques enhanced capabilities"
    },
    {
      "target": ".github/skills/change-management/SKILL.md",
      "type": "relates",
      "strength": 0.7,
      "description": "Organizational changes flow through HR processes",
      "when": "HR people operations connects to change management",
      "yields": "change management patterns and guidance"
    },
    {
      "target": ".github/skills/pii-privacy-regulations/SKILL.md",
      "type": "requires",
      "strength": 0.8,
      "description": "Employee data is PII — strict privacy and retention rules apply",
      "when": "HR people operations depends on PII privacy regulations",
      "yields": "PII privacy regulations required patterns and guidance"
    },
    {
      "target": ".github/skills/career-development/SKILL.md",
      "type": "extends",
      "strength": 0.7,
      "description": "HR manages career pathing, internal mobility, and professional development programs",
      "when": "HR people operations enhances career development",
      "yields": "career development enhanced capabilities"
    },
    {
      "target": ".github/skills/business-analysis/SKILL.md",
      "type": "relates",
      "strength": 0.5,
      "description": "HR analytics and workforce planning require business analysis skills",
      "when": "HR people operations connects to business analysis",
      "yields": "business analysis patterns and guidance"
    }
  ],
  "activationContexts": [
    "hiring",
    "recruiting",
    "onboarding",
    "performance review",
    "compensation",
    "employee",
    "workforce",
    "talent acquisition",
    "HR",
    "human resources",
    "people operations",
    "termination",
    "offboarding",
    "labor law",
    "FMLA",
    "ADA"
  ],
  "notes": "Talent acquisition, employee lifecycle, compensation, labor law, organizational development",
  "schemaVersion": "2.0.0",
  "activationTriggers": [
    "hiring",
    "recruiting",
    "onboarding",
    "performance review",
    "compensation",
    "employee",
    "workforce",
    "talent acquisition",
    "HR",
    "human resources",
    "people operations",
    "termination",
    "offboarding",
    "labor law",
    "FMLA",
    "ADA"
  ]
}
